tyler_efm_client/__init__.py
tyler_efm_client/client.py
tyler_efm_client-1.0.0a2.dist-info/licenses/LICENSE
tyler_efm_client-1.0.0a2.dist-info/METADATA
tyler_efm_client-1.0.0a2.dist-info/WHEEL
tyler_efm_client-1.0.0a2.dist-info/top_level.txt
tyler_efm_client-1.0.0a2.dist-info/RECORD
