Metadata-Version: 2.4
Name: tyler-efm-client
Version: 1.0.0a2
Summary: Python SDK for Tyler Technologies Electronic Filing Manager (EFM) Services
Author-email: Tyler Technologies ECF Integration Team <ecf-support@tylertech.com>
Maintainer-email: Tyler Technologies ECF Integration Team <ecf-support@tylertech.com>
License-Expression: MIT
Project-URL: Homepage, https://github.com/tyler-technologies/cj-esol-efm-client-python
Project-URL: Documentation, https://github.com/tyler-technologies/cj-esol-efm-client-python#readme
Project-URL: Repository, https://github.com/tyler-technologies/cj-esol-efm-client-python.git
Project-URL: Bug Reports, https://github.com/tyler-technologies/cj-esol-efm-client-python/issues
Keywords: tyler,efm,ecf,electronic-filing,court-filing,soap,ws-security,legal,court,filing
Platform: UNKNOWN
Classifier: Development Status :: 3 - Alpha
Classifier: Intended Audience :: Developers
Classifier: Operating System :: OS Independent
Classifier: Programming Language :: Python :: 3
Classifier: Programming Language :: Python :: 3.9
Classifier: Programming Language :: Python :: 3.10
Classifier: Programming Language :: Python :: 3.11
Classifier: Programming Language :: Python :: 3.12
Classifier: Topic :: Software Development :: Libraries :: Python Modules
Classifier: Topic :: Internet :: WWW/HTTP :: Dynamic Content
Classifier: Topic :: Office/Business :: Financial
Classifier: Topic :: System :: Networking
Requires-Python: >=3.9
License-File: LICENSE
Requires-Dist: requests>=2.25.0
Requires-Dist: cryptography>=3.4.0
Requires-Dist: lxml>=4.6.0
Provides-Extra: dev
Requires-Dist: pytest>=6.0.0; extra == "dev"
Requires-Dist: pytest-cov>=2.10.0; extra == "dev"
Requires-Dist: black>=21.0.0; extra == "dev"
Requires-Dist: flake8>=3.8.0; extra == "dev"
Requires-Dist: mypy>=0.812; extra == "dev"
Dynamic: license-file
